tree_sitter_moonbit/__init__.py
tree_sitter_moonbit/__init__.pyi
tree_sitter_moonbit/_binding.abi3.so
tree_sitter_moonbit/binding.c
tree_sitter_moonbit/py.typed
tree_sitter_moonbit/queries/folds.scm
tree_sitter_moonbit/queries/highlights.scm
tree_sitter_moonbit/queries/indents.scm
tree_sitter_moonbit/queries/injections.scm
tree_sitter_moonbit/queries/locals.scm
tree_sitter_moonbit/queries/textobjects.scm
tree_sitter_moonbit-1.0.0.dist-info/LICENSE
tree_sitter_moonbit-1.0.0.dist-info/METADATA
tree_sitter_moonbit-1.0.0.dist-info/WHEEL
tree_sitter_moonbit-1.0.0.dist-info/top_level.txt
tree_sitter_moonbit-1.0.0.dist-info/RECORD
